scc_pyteam/__init__.py
scc_pyteam/cookiecutter_templates/__init__.py
scc_pyteam/cookiecutter_templates/django_template/cookiecutter.json
scc_pyteam/cookiecutter_templates/django_template/setup.py
scc_pyteam/cookiecutter_templates/django_template/{{cookiecutter.project_name}}/.bumpversion.cfg
scc_pyteam/cookiecutter_templates/django_template/{{cookiecutter.project_name}}/.dockerignore
scc_pyteam/cookiecutter_templates/django_template/{{cookiecutter.project_name}}/.flake8
scc_pyteam/cookiecutter_templates/django_template/{{cookiecutter.project_name}}/.gitignore
scc_pyteam/cookiecutter_templates/django_template/{{cookiecutter.project_name}}/.pre-commit-config.yaml
scc_pyteam/cookiecutter_templates/django_template/{{cookiecutter.project_name}}/.vscode/settings.json
scc_pyteam/cookiecutter_templates/django_template/{{cookiecutter.project_name}}/Dockerfile
scc_pyteam/cookiecutter_templates/django_template/{{cookiecutter.project_name}}/Makefile
scc_pyteam/cookiecutter_templates/django_template/{{cookiecutter.project_name}}/README.md
scc_pyteam/cookiecutter_templates/django_template/{{cookiecutter.project_name}}/configs/__init__.py
scc_pyteam/cookiecutter_templates/django_template/{{cookiecutter.project_name}}/configs/gunicorn_config.py
scc_pyteam/cookiecutter_templates/django_template/{{cookiecutter.project_name}}/configs/uvicorn.py
scc_pyteam/cookiecutter_templates/django_template/{{cookiecutter.project_name}}/data/postgres/.gitignore
scc_pyteam/cookiecutter_templates/django_template/{{cookiecutter.project_name}}/data/redis/.gitignore
scc_pyteam/cookiecutter_templates/django_template/{{cookiecutter.project_name}}/docs/index.md
scc_pyteam/cookiecutter_templates/django_template/{{cookiecutter.project_name}}/docs/tutorials.md
scc_pyteam/cookiecutter_templates/django_template/{{cookiecutter.project_name}}/envs/.gitignore
scc_pyteam/cookiecutter_templates/django_template/{{cookiecutter.project_name}}/envs/example.env
scc_pyteam_template_tools-0.2.6.dist-info/METADATA
scc_pyteam_template_tools-0.2.6.dist-info/WHEEL
scc_pyteam_template_tools-0.2.6.dist-info/entry_points.txt
scc_pyteam_template_tools-0.2.6.dist-info/RECORD
